{
"autoplayBgm":false,"autoplayBgs":false,"battleback1Name":"","battleback2Name":"","bgm":{"name":"","pan":0,"pitch":100,"volume":90},"bgs":{"name":"","pan":0,"pitch":100,"volume":90},"disableDashing":false,"displayName":"","encounterList":[],"encounterStep":30,"height":13,"note":"<ulds> {\n\"name\": \"276\",\n\"x\": \"this.rx(1)\",\n\"y\": \"this.ry(1)\",\n\"z\": \"3\",\n\"loop\": true\n} </ulds>\n","parallaxLoopX":false,"parallaxLoopY":false,"parallaxName":"","parallaxShow":true,"parallaxSx":0,"parallaxSy":0,"scrollType":0,"specifyBattleback":false,"tilesetId":51,"width":17,
"data":[0,0,0,0,0,0,0,0,0,0,0,0,0,0,0,0,0,0,0,0,0,0,0,0,0,0,0,0,0,0,0,0,0,0,0,0,0,0,1552,1552,1552,1552,1552,1552,1552,1552,1552,0,0,0,0,0,0,0,0,1552,1552,1552,1552,1552,1552,1552,1552,1552,0,0,0,0,0,0,0,0,1552,1552,1552,1552,1552,1552,1552,1552,1552,0,0,0,0,0,0,0,0,1552,1552,1554,1554,1554,1554,1554,1552,1552,0,0,0,0,0,0,0,0,1552,1552,1554,1554,1554,1554,1554,1552,1552,0,0,0,0,0,0,0,0,1552,1552,1554,1554,1554,1554,1554,1552,1552,0,0,0,0,0,0,0,0,1552,1552,1552,1552,1552,1552,1552,1552,1552,0,0,0,0,0,0,0,0,1552,1552,1552,1552,1552,1552,1552,1552,1552,0,0,0,0,0,0,0,0,1552,1552,1552,1552,1552,1552,1552,1552,1552,0,0,0,0,0,0,0,0,0,0,0,0,0,0,0,0,0,0,0,0,0,0,0,0,0,0,0,0,0,0,0,0,0,0,0,0,0,0,0,0,0,0,0,0,0,0,0,0,0,0,0,0,0,0,0,0,0,0,0,0,0,0,0,0,0,0,0,0,0,0,0,0,0,0,0,0,0,0,0,0,0,0,0,0,0,0,0,0,0,0,0,0,0,0,0,0,0,0,0,0,0,0,0,0,0,0,0,0,0,0,0,0,0,0,0,0,0,0,0,0,0,0,0,0,0,0,0,0,0,0,0,0,0,0,0,0,0,0,0,0,0,0,0,0,0,0,0,0,0,0,0,0,0,0,0,0,0,0,0,0,0,0,0,0,0,0,0,0,0,0,0,0,0,0,0,0,0,0,0,0,0,0,0,0,0,0,0,0,0,0,0,0,0,0,0,0,0,0,0,0,0,0,0,0,0,0,0,0,0,0,0,0,0,0,0,0,0,0,0,0,0,0,0,0,0,0,0,0,0,0,0,0,0,0,0,0,0,0,0,0,0,0,0,0,0,0,0,0,0,0,0,0,0,0,0,0,0,0,0,0,0,0,0,0,0,0,0,0,0,0,0,0,0,0,0,0,0,0,0,0,0,0,0,0,0,0,0,0,0,0,0,0,0,0,0,0,0,346,0,355,603,568,354,346,346,346,0,0,0,0,0,0,0,0,354,0,347,577,347,0,322,0,354,0,0,0,0,0,0,0,0,346,346,347,288,337,337,345,368,346,0,0,0,0,0,0,0,0,0,0,0,0,0,0,280,376,354,0,0,0,0,0,0,0,0,0,0,0,0,0,0,0,346,0,0,0,0,0,0,0,0,0,354,346,281,0,281,0,281,346,354,0,0,0,0,0,0,0,0,346,354,0,0,602,354,355,0,346,0,0,0,0,0,0,0,0,354,0,347,577,329,0,577,0,354,0,0,0,0,0,0,0,0,346,0,355,603,337,354,355,346,346,0,0,0,0,0,0,0,0,0,0,0,0,0,0,0,0,0,0,0,0,0,0,0,0,0,0,0,0,0,0,0,0,0,0,0,0,0,0,0,0,0,0,0,0,0,0,0,0,0,0,0,0,0,0,0,0,0,0,0,0,0,0,0,0,0,0,0,0,0,0,0,0,0,0,0,0,568,354,602,336,337,569,369,347,568,0,0,0,0,0,0,0,0,577,346,576,328,329,346,377,346,577,0,0,0,0,0,0,0,0,572,568,288,281,281,281,290,344,572,0,0,0,0,0,0,0,0,354,354,280,0,0,0,296,281,281,0,0,0,0,0,0,0,0,347,335,280,0,0,0,280,577,347,0,0,0,0,0,0,0,0,320,370,304,281,289,281,306,611,320,0,0,0,0,0,0,0,0,344,378,355,354,280,603,371,346,344,0,0,0,0,0,0,0,0,352,346,576,328,280,346,379,354,352,0,0,0,0,0,0,0,0,568,354,602,336,280,569,346,347,568,0,0,0,0,0,0,0,0,0,0,0,0,0,0,0,0,0,0,0,0,0,0,0,0,0,0,0,0,0,0,0,0,0,0,0,0,0,0,0,0,0,0,0,0,0,0,0,0,0,0,0,0,0,0,0,0,0,0,0,0,0,0,0,0,0,0,0,0,0,0,0,0,0,0,0,0,0,0,0,0,0,0,0,0,0,0,0,0,0,0,0,0,0,0,0,0,0,0,0,0,0,0,0,0,0,0,0,0,0,0,0,0,0,0,0,0,0,0,0,0,0,0,0,0,0,0,0,0,0,0,0,0,0,0,0,0,0,0,0,0,0,0,0,0,0,0,0,0,0,0,0,0,0,0,0,0,0,0,0,0,0,0,0,0,0,0,0,0,0,0,0,0,0,0,0,0,0,0,0,0,0,0,0,0,0,0,0,0,0,0,0,0,0,0,0,0,0,0,0,0,0,0,0,0,0,0,0,0,0,0,0,0,0,0,0,0,0,0,0,0,0,0,0,0,0,0,0,0,0,0,0,0,0,0,0,0,0,0,0,0,0,0,0,0,0,0,0,0,0,0,0,0,0,0,0,0,0,0,0,0,0,0,0,0,0,0,0,0,0,0,0,0,0,0,0,0,0,0,0,0,0,0,0,0,0,0,0,0,0,0,0,0,0,0,0,0,0,0,0,0,0,0,0,0,0,0,0,0,0,0,0,0,0,0,0,0,0,0,0,0,0,0,0,0,0,0,0,0,0,0,0,0,0,0,0,0,0,0,0,0,0,0,0,0,0,0,0,0,0,0,0,0,0,0,0,0,0,0,0,0,0,0,0,0,0,0,0,0,0,0,0,0,0,0,0,0,0,0,0,0,0,0,0,0,0,0,0,0,0,0,0,0,0,0,0,0,0,0,0,0,0,0,0,0,0,0,0,0,0,0,0,0,0,0,0,0,0,0,0,0,0,0,0,0,0,0,0,0,0,0,0,0,0,0,0,0,0,0,0,0,0,0,0,0,0,0,0,0,0,0,0,0,0,0,0,0,0,0,0,0,0,0,0,0,0,0,0,0,0,0,0,0,0,0,0,0,0,0,0,0],
"events":[
null,
{"id":1,"name":"巨人","note":"","pages":[{"conditions":{"actorId":1,"actorValid":false,"itemId":1,"itemValid":false,"selfSwitchCh":"A","selfSwitchValid":false,"switch1Id":1,"switch1Valid":false,"switch2Id":1,"switch2Valid":false,"variableId":1,"variableValid":false,"variableValue":0},"directionFix":false,"image":{"tileId":0,"characterName":"$风纪委员1","direction":8,"pattern":1,"characterIndex":0},"list":[{"code":0,"indent":0,"parameters":[]}],"moveFrequency":5,"moveRoute":{"list":[{"code":45,"parameters":[" this._chaseSpeed = 5"],"indent":0},{"code":45,"parameters":[" this._seePlayer = true"],"indent":0},{"code":45,"parameters":["this._chaseRange = 4"],"indent":0},{"code":3,"indent":null},{"code":3,"indent":null},{"code":3,"indent":null},{"code":3,"indent":null},{"code":3,"indent":null},{"code":3,"indent":null},{"code":3,"indent":null},{"code":3,"indent":null},{"code":3,"indent":null},{"code":3,"indent":null},{"code":3,"indent":null},{"code":15,"parameters":[120],"indent":null},{"code":2,"indent":null},{"code":2,"indent":null},{"code":2,"indent":null},{"code":2,"indent":null},{"code":2,"indent":null},{"code":2,"indent":null},{"code":2,"indent":null},{"code":2,"indent":null},{"code":2,"indent":null},{"code":2,"indent":null},{"code":2,"indent":null},{"code":15,"parameters":[120],"indent":null},{"code":0,"parameters":[]}],"repeat":true,"skippable":false,"wait":false},"moveSpeed":4,"moveType":0,"priorityType":1,"stepAnime":false,"through":false,"trigger":2,"walkAnime":true},{"conditions":{"actorId":1,"actorValid":false,"itemId":1,"itemValid":false,"selfSwitchCh":"A","selfSwitchValid":false,"switch1Id":479,"switch1Valid":true,"switch2Id":1,"switch2Valid":false,"variableId":1,"variableValid":false,"variableValue":0},"directionFix":false,"image":{"characterIndex":0,"characterName":"","direction":2,"pattern":0,"tileId":0},"list":[{"code":0,"indent":0,"parameters":[]}],"moveFrequency":3,"moveRoute":{"list":[{"code":0,"parameters":[]}],"repeat":true,"skippable":false,"wait":false},"moveSpeed":3,"moveType":0,"priorityType":0,"stepAnime":false,"through":false,"trigger":0,"walkAnime":true}],"x":8,"y":11},
{"id":2,"name":"EV002","note":"","pages":[{"conditions":{"actorId":1,"actorValid":false,"itemId":1,"itemValid":false,"selfSwitchCh":"A","selfSwitchValid":false,"switch1Id":1,"switch1Valid":false,"switch2Id":1,"switch2Valid":false,"variableId":1,"variableValid":false,"variableValue":0},"directionFix":false,"image":{"characterIndex":0,"characterName":"","direction":2,"pattern":0,"tileId":0},"list":[{"code":223,"indent":0,"parameters":[[0,0,0,0],1,true]},{"code":205,"indent":0,"parameters":[1,{"list":[{"code":39,"indent":null},{"code":0}],"repeat":false,"skippable":false,"wait":true}]},{"code":505,"indent":0,"parameters":[{"code":39,"indent":null}]},{"code":222,"indent":0,"parameters":[]},{"code":241,"indent":0,"parameters":[{"name":"Battle_-_Steel_Soldiers","volume":70,"pitch":100,"pan":0}]},{"code":230,"indent":0,"parameters":[60]},{"code":250,"indent":0,"parameters":[{"name":"Explosion2","volume":25,"pitch":100,"pan":0}]},{"code":225,"indent":0,"parameters":[2,4,60,true]},{"code":230,"indent":0,"parameters":[80]},{"code":250,"indent":0,"parameters":[{"name":"Explosion2","volume":45,"pitch":100,"pan":0}]},{"code":225,"indent":0,"parameters":[3,6,60,true]},{"code":230,"indent":0,"parameters":[80]},{"code":205,"indent":0,"parameters":[1,{"list":[{"code":40,"indent":null},{"code":37,"indent":null},{"code":4,"indent":null},{"code":38,"indent":null},{"code":0}],"repeat":false,"skippable":false,"wait":true}]},{"code":505,"indent":0,"parameters":[{"code":40,"indent":null}]},{"code":505,"indent":0,"parameters":[{"code":37,"indent":null}]},{"code":505,"indent":0,"parameters":[{"code":4,"indent":null}]},{"code":505,"indent":0,"parameters":[{"code":38,"indent":null}]},{"code":250,"indent":0,"parameters":[{"name":"Explosion2","volume":65,"pitch":100,"pan":0}]},{"code":225,"indent":0,"parameters":[5,6,60,true]},{"code":230,"indent":0,"parameters":[80]},{"code":205,"indent":0,"parameters":[1,{"list":[{"code":40,"indent":null},{"code":4,"indent":null},{"code":0}],"repeat":false,"skippable":false,"wait":true}]},{"code":505,"indent":0,"parameters":[{"code":40,"indent":null}]},{"code":505,"indent":0,"parameters":[{"code":4,"indent":null}]},{"code":250,"indent":0,"parameters":[{"name":"Explosion2","volume":85,"pitch":100,"pan":0}]},{"code":225,"indent":0,"parameters":[7,8,60,true]},{"code":230,"indent":0,"parameters":[120]},{"code":221,"indent":0,"parameters":[]},{"code":201,"indent":0,"parameters":[0,395,14,4,2,0]},{"code":0,"indent":0,"parameters":[]}],"moveFrequency":3,"moveRoute":{"list":[{"code":0,"parameters":[]}],"repeat":true,"skippable":false,"wait":false},"moveSpeed":3,"moveType":0,"priorityType":0,"stepAnime":false,"through":false,"trigger":3,"walkAnime":true}],"x":14,"y":2},
null
]
}